kite/__init__.py
kite/hello.py
kiteai-0.0.1.dist-info/METADATA
kiteai-0.0.1.dist-info/WHEEL
kiteai-0.0.1.dist-info/RECORD
